danitonapi/__init__.py
danitonapi/api.py
danitonapi-1.7.dist-info/METADATA
danitonapi-1.7.dist-info/WHEEL
danitonapi-1.7.dist-info/top_level.txt
danitonapi-1.7.dist-info/RECORD
