Metadata-Version: 2.1
Name: danitonapi
Version: 1.7
Summary: A global Artificial Intelligence Network called Daniton
Home-page: https://github.com/Dart2004/DanitonAPI/
Author: Daniton999
Author-email: zombieservers123@gmail.com
License: UNKNOWN
Project-URL: Bug Tracker, https://github.com/Dart2004/DanitonAPI/issues
Platform: UNKNOWN
Classifier: Programming Language :: Python :: 3
Classifier: License :: OSI Approved :: MIT License
Classifier: Operating System :: OS Independent
Requires-Python: >=3.6
